Metadata-Version: 1.1
Name: google-oauth
Version: 1.0.0
Summary: Google OAuth 2.0 for Server to Server applications implementation. Performs JWT-based access token retrieval for Google APIs.
Home-page: https://github.com/miedzinski/google-oauth2-service
Author: Dominik Miedziński
Author-email: UNKNOWN
License: MIT License
Keywords: google oauth oauth2 api service jwt
Platform: UNKNOWN
Classifier: Intended Audience :: Developers
Classifier: License :: OSI Approved :: MIT License
Classifier: Programming Language :: Python
Classifier: Programming Language :: Python :: 2
Classifier: Programming Language :: Python :: 3
Classifier: Topic :: Internet
